[{"id":"AED","text":"UAE Dirham"},{"id":"AFN","text":"Afghanske Afghanere"},{"id":"ALL","text":"Albansk Lek"},{"id":"AMD","text":"Armensk Dram"},{"id":"ANG","text":"Netherlands Antillean Guilder"},{"id":"AOA","text":"Angolanske Kwanza"},{"id":"ARS","text":"Argentinsk Peso"},{"id":"AUD","text":"Australsk Dollar"},{"id":"AWG","text":"Aruban Florin"},{"id":"AZN","text":"Aserbajdsjan Manat"},{"id":"BAM","text":"Bosnia-Herzegovina Cabriolet Mark"},{"id":"BBD","text":"Barbadisk Dollar"},{"id":"BCN","text":"Bytecoin"},{"id":"BDT","text":"Bangladesh-Taka"},{"id":"BGN","text":"Bulgarske Lev"},{"id":"BHD","text":"Bahraini Dinar"},{"id":"BIF","text":"Burundian Franc"},{"id":"BMD","text":"Bermudan Dollar"},{"id":"BND","text":"Brunei-dollar"},{"id":"BOB","text":"Bolivian Boliviano"},{"id":"BRL","text":"Brasiliansk Real"},{"id":"BSD","text":"Bahamisk Dollar"},{"id":"BTC","text":"Bitcoin"},{"id":"BTN","text":"Bhutansk Ngultrum"},{"id":"BTS","text":"BitShares"},{"id":"BWP","text":"Botswana Pula"},{"id":"BYN","text":"Hviterussisk Rubel"},{"id":"BYR","text":"Hviterussisk Rubel (Før 2016)"},{"id":"BZD","text":"Belize Dollar"},{"id":"CAD","text":"Kanadisk Dollar"},{"id":"CDF","text":"Kongolesisk Franc"},{"id":"CHF","text":"Sveitsiske Franc"},{"id":"CLF","text":"Chilenske Kontoenhet (UF)"},{"id":"CLP","text":"Chilensk Peso"},{"id":"CNH","text":"Chinese Yuan (Offshore)"},{"id":"CNY","text":"Kinesisk Yuan"},{"id":"COP","text":"Colombiansk Peso"},{"id":"CRC","text":"Costa Rica Colón"},{"id":"CUC","text":"Kubansk Konvertibel Peso"},{"id":"CUP","text":"Cubansk Peso"},{"id":"CVE","text":"Kapp Verdean Escudo"},{"id":"CYP","text":"Kypriotiske Pund"},{"id":"CZK","text":"Tsjekkia Koruna"},{"id":"DASH","text":"Bindestrek"},{"id":"DJF","text":"Djiboutian Franc"},{"id":"DKK","text":"Danske Krone"},{"id":"DOGE","text":"Dogecoin"},{"id":"DOP","text":"Dominikanske Peso"},{"id":"DZD","text":"Algerie Dinar"},{"id":"EAC","text":"EarthCoin"},{"id":"EEK","text":"Estiske Kroon"},{"id":"EGP","text":"Egyptisk Pund"},{"id":"EMC","text":"Emercoin"},{"id":"ERN","text":"Eritreisk Nakfa"},{"id":"ETB","text":"Etiopiske Birr"},{"id":"ETH","text":"Ethereum"},{"id":"EUR","text":"Euro"},{"id":"FCT","text":"Factom"},{"id":"FJD","text":"Fijiansk Dollar"},{"id":"FKP","text":"Falkland Islands Pound"},{"id":"FTC","text":"Feathercoin"},{"id":"GBP","text":"Britiske Pund Sterling"},{"id":"GEL","text":"Georgisk Lari"},{"id":"GGP","text":"Guernsey Pound"},{"id":"GHS","text":"Ghanaian Cedi"},{"id":"GIP","text":"Gibraltar Pund"},{"id":"GMD","text":"Gambian Dalasi"},{"id":"GNF","text":"Guinean Franc"},{"id":"GRD","text":"Gresk Drachma"},{"id":"GTQ","text":"Guatemalas Quetzal"},{"id":"GYD","text":"Guyanese Dollar"},{"id":"HKD","text":"Hong Kong Dollar"},{"id":"HNL","text":"Honduranske Lempira"},{"id":"HRK","text":"Kroatisk Kuna"},{"id":"HTG","text":"Haitisk Gourde"},{"id":"HUF","text":"Ungarsk Forint"},{"id":"IDR","text":"Indonesiske Rupiah"},{"id":"IEP","text":"Irish Punt"},{"id":"ILS","text":"Israelsk Nye Sheqel"},{"id":"IMP","text":"Manx Pund"},{"id":"INR","text":"Indian Rupee"},{"id":"IQD","text":"Irakisk Dinar"},{"id":"IRR","text":"Iransk Rial"},{"id":"ISK","text":"Islandske Kroner"},{"id":"JEP","text":"Jersey Pound"},{"id":"JMD","text":"Jamaicanske Dollar"},{"id":"JOD","text":"Jordanske Dinar"},{"id":"JPY","text":"Japansk Yen"},{"id":"KES","text":"Kenyansk Shilling"},{"id":"KGS","text":"Kyrgyzstani Som"},{"id":"KHR","text":"Kambodsjanske Riel"},{"id":"KMF","text":"Komikeren Franc"},{"id":"KPW","text":"Nord-Korea Vant"},{"id":"KRW","text":"Sør-Korea Vant"},{"id":"KWD","text":"Kuwaiti Dinar"},{"id":"KYD","text":"Cayman Islands Dollar"},{"id":"KZT","text":"Kazakhstani Tenge"},{"id":"LAK","text":"Laotian Kip"},{"id":"LBP","text":"Libanesisk Pund"},{"id":"LD","text":"Linden Dollar"},{"id":"LKR","text":"Sri Lanka Rupee"},{"id":"LRD","text":"Liberian Dollar"},{"id":"LSL","text":"Lesotho Loti"},{"id":"LTC","text":"Litecoin"},{"id":"LTL","text":"Litauiske Litas"},{"id":"LVL","text":"Latviske Lats"},{"id":"LYD","text":"Libyan Dinar"},{"id":"MAD","text":"Marokkansk Dirham"},{"id":"MDL","text":"Moldovanske Leu"},{"id":"MGA","text":"Malagasy Ariary"},{"id":"MKD","text":"Makedonsk Denar"},{"id":"MMK","text":"Myanmar (burmesisk) Kyat"},{"id":"MNT","text":"Mongolske Tugrik"},{"id":"MOP","text":"Macanese Pataca"},{"id":"MRO","text":"Mauretanske Ouguiya (Før 2018)"},{"id":"MRU","text":"Mauretanske Ouguiya"},{"id":"MTL","text":"Maltesisk Lira"},{"id":"MUR","text":"Mauritian Rupee"},{"id":"MVR","text":"Maldivian Rufiyaa"},{"id":"MWK","text":"Malawisk Kwacha"},{"id":"MXN","text":"Meksikansk Peso"},{"id":"MYR","text":"Malaysisk Ringgit"},{"id":"MZN","text":"Mosambiksk Metisk"},{"id":"NAD","text":"Namibisk Dollar"},{"id":"NGN","text":"Nigerianske Naira"},{"id":"NIO","text":"Nicaraguan Córdoba"},{"id":"NMC","text":"Namecoin"},{"id":"NOK","text":"Norsk Krone"},{"id":"NPR","text":"Nepalske Rupier"},{"id":"NVC","text":"NovaCoin"},{"id":"NXT","text":"Nxt"},{"id":"NZD","text":"New Zealand Dollar"},{"id":"OMR","text":"Omani Rial"},{"id":"PAB","text":"Panamansk Balboa"},{"id":"PEN","text":"Peruanske Nuevo Sol"},{"id":"PGK","text":"Papua Ny-Guinean Kina"},{"id":"PHP","text":"Filippinsk Peso"},{"id":"PKR","text":"Pakistansk Rupee"},{"id":"PLN","text":"Polske Zloty"},{"id":"PPC","text":"Peercoin"},{"id":"PYG","text":"Paraguayanske Guarani"},{"id":"QAR","text":"Qatari Rial"},{"id":"RBY","text":"Rubycoin"},{"id":"RON","text":"Rumensk Leu"},{"id":"RSD","text":"Serbisk Dinar"},{"id":"RUB","text":"Russisk Rubel"},{"id":"RWF","text":"Rwandisk Franc"},{"id":"SAR","text":"Saudi Riyal"},{"id":"SBD","text":"Solomon Islands Dollar"},{"id":"SCR","text":"Seychellois Rupee"},{"id":"SDG","text":"Sudanesiske Pund"},{"id":"SEK","text":"Svensk Krona"},{"id":"SGD","text":"Singapore Dollar"},{"id":"SHP","text":"Saint Helena Pound"},{"id":"SIT","text":"Slovensk Tolar"},{"id":"SKK","text":"Slovakisk Koruna"},{"id":"SLL","text":"Sierra Leonean Leone"},{"id":"SOS","text":"Somalisk Shilling"},{"id":"SRD","text":"Surinamsk Dollar"},{"id":"SSP","text":"Sør-Sudanesiske Pund"},{"id":"STD","text":"São Tomé Og Príncipe Dobra (Før 2018)"},{"id":"STN","text":"São Tomé Og Príncipe Dobra"},{"id":"STR","text":"Stellar"},{"id":"SVC","text":"Salvadoranske Colón"},{"id":"SYP","text":"Syriske Pund"},{"id":"SZL","text":"Swazi Lilangeni"},{"id":"THB","text":"Thai Baht"},{"id":"TJS","text":"Tajikistani Somoni"},{"id":"TMT","text":"Turkmenistani Manat"},{"id":"TND","text":"Tunisiske Dinar"},{"id":"TOP","text":"Tongansk Paʻanga"},{"id":"TRY","text":"Tyrkisk Lira"},{"id":"TTD","text":"Trinidad Og Tobago Dollar"},{"id":"TWD","text":"Ny Taiwan-dollar"},{"id":"TZS","text":"Tanzaniansk Shilling"},{"id":"UAH","text":"Ukrainske Hryvnian"},{"id":"UGX","text":"Ugandisk Shilling"},{"id":"USD","text":"Amerikanske Dollar"},{"id":"UYU","text":"Uruguayansk Peso"},{"id":"UZS","text":"Usbekistan Som"},{"id":"VEB","text":"Venezuelanske Bolívar (Før 2008)"},{"id":"VEF","text":"Venezuelanske Bolívar Fuerte (Gammel)"},{"id":"VEF_BLKMKT","text":"Venezuelanske Bolívar (Det Svarte Markedet)"},{"id":"VEF_DICOM","text":"Venezuelanske Bolívar (DICOM)"},{"id":"VEF_DIPRO","text":"Venezuelanske Bolívar (DIPRO)"},{"id":"VEF_SIMADI","text":"Venezuelanske Bolívar (SIMADI)"},{"id":"VES","text":"Venezuelanske Bolívar Soberano"},{"id":"VND","text":"Vietnamesiske Dong"},{"id":"VTC","text":"VertCoin"},{"id":"VUV","text":"Vanuatu Vatu"},{"id":"WST","text":"Samoan Tala"},{"id":"XAF","text":"CFA Franc BEAC"},{"id":"XAG","text":"Sølvunse"},{"id":"XAU","text":"Gull Unse"},{"id":"XCD","text":"Øst-karibisk Dollar"},{"id":"XCP","text":"Kobberunse"},{"id":"XDR","text":"Spesielle Tegnerettigheter"},{"id":"XEM","text":"Nem"},{"id":"XMR","text":"Monero"},{"id":"XOF","text":"CFA Franc BCEAO"},{"id":"XPD","text":"Palladium Ounce"},{"id":"XPF","text":"CFP Franc"},{"id":"XPM","text":"Primecoin"},{"id":"XPT","text":"Platinum Ounce"},{"id":"XRP","text":"Ripple"},{"id":"YER","text":"Jemenittisk Rial"},{"id":"ZAR","text":"Sør-afrikansk Rand"},{"id":"ZMK","text":"Zambian Kwacha (Før 2013)"},{"id":"ZMW","text":"Zambian Kwacha"},{"id":"ZWD","text":"Zimbabwean Dollar (Før 2009)"},{"id":"ZWL","text":"Zimbabwisk Dollar"}]